Metadata-Version: 2.1
Name: lyyocr
Version: 1.1
Summary: lyyocr for lyy
Author: lyy
Author-email: 
License: MIT
License-File: LICENSE
